[
    {
        "id": 1,
        "name": "adksfnnk",
        "sname": "kjsadekj",
        "nr": "353525",
        "email": "ai@ai.com"
    },
    {
        "id": "2",
        "name": "gugugu",
        "sname": "asdsdad",
        "nr": "1215355243532",
        "email": "ai@ai.com"
    },
    {
        "id": "3",
        "name": "lalala",
        "sname": "asdaaf",
        "nr": "352562626",
        "email": "ak@ak.com"
    },
    {
        "id": "4",
        "name": "ukulele",
        "sname": "labablbalalbla",
        "nr": "824637529876",
        "email": "asa@aksfa.com"
    },
    {
        "id": "5",
        "name": "fgjfjfjfjfjfj",
        "sname": "dsggsgg",
        "nr": "35523",
        "email": "ak@ak.com"
    }
]